{
  "id": "parithosh",
  "name": "Parithosh",
  "bio": "I am an Ethereum enthusiast with a deep love for all things servers. I incorporated Ethereum into my Master’s thesis and loved the experience so much as to make it my full time job. I currently work in the DevOps team of the Ethereum Foundation and I mainly focus on the Ethereum protocol upgrades. I’m also an avid photographer with a specific interest in Landscape and Travel photography.",
  "eventId": "protocol_berg",
  "photo": "https://speak.protocol.berlin/media/avatars/x5MkzrAf_400x400_410A3ST.jpg"
}
