{
  "id": "daimo",
  "name": "Daimo",
  "description": "",
  "start": 1699266600000,
  "end": 1699267500000,
  "stageId": "theater",
  "speakers": [
    {
      "id": "althea_allen",
      "name": "Althea Allen \n",
      "bio": "No description",
      "eventId": "zuconnect__zk_track"
    },
    {
      "id": "nalin_bhardwaj",
      "name": "Nalin Bhardwaj",
      "bio": "No description",
      "eventId": "zuconnect__zk_track"
    },
    {
      "id": "dc_posch",
      "name": "DC Posch",
      "bio": "No description",
      "eventId": "zuconnect__zk_track"
    }
  ],
  "playbackId": "",
  "eventId": "zuconnect__zk_track",
  "coverImage": "/sessions/zuconnect__zk_track/daimo.jpg"
}