{"id":"developing_a_dao_contract_in_sway","name":"Developing a DAO Contract in Sway","description":"Learn how to develop a performant and safe DAO contract in Sway, the next-generation smart contract language from Fuel Labs. Feel free to bring a laptop, this will be interactive! Install dependencies using this tool: https://github.com/FuelLabs/fuelup","start":"2022-09-16T19:30:00.000Z","end":"2022-09-16T20:15:00.000Z","stageId":"farabeuf_amphitheater","speakers":[{"id":"alex_hansen","name":"Alex Hansen","bio":"No description","eventId":"ethberlin_2022"}],"videoUrl":"","playbackId":"","eventId":"ethberlin_2022"}