{"id":"the_sorvereign_creator","name":"The Sorvereign Creator","description":"Alec Empire’s talk about being an artist in web3, how to understand music and hacker culture in cyberspace and why Ethereum will give rise to the Sovereign Creator.","start":"2022-09-18T12:30:00.000Z","end":"2022-09-18T13:00:00.000Z","stageId":"farabeuf_amphitheater","speakers":[{"id":"alec_empire","name":"Alec Empire","bio":"No description","eventId":"ethberlin_2022"}],"videoUrl":"","playbackId":"","eventId":"ethberlin_2022"}