{
  "id": "swarm_summit_2",
  "name": "Swarm summit 2",
  "description": "As the summer light symbolically vanquished the darkness on 21 June, Swarm network kicked off its three-day Swarm Virtual Summit. This year, the network’s global community gathered in the virtual world, giving all its diverse members a chance to watch and listen to leading voices and keen enthusiasts across different fields on the online stage.",
  "start": "2023-12-14T00:00:00.000Z",
  "end": "2023-12-14T00:00:00.000Z",
  "location": "virtual",
  "organizationId": "swarm",
  "dataImporter": [
    {
      "type": "gsheet",
      "config": {
        "sheetId": "1-MIyFvZMjHMfa5UhoesA4hB5s9YHisBWoUyrtG0l_fg",
        "apiKey": "s"
      }
    }
  ],
  "eventCover": "swarm_logo.jpeg",
  "logo": "swarm_logo.jpeg",
  "banner": "swarm_banner.png",
  "website": "",
  "archiveMode": false,
  "timezone": "Europe/Berlin",
  "accentColor": "#ff7a00"
}
