{"id":"the_crypto_mullet_building_web_3_in_a_web_2_world","name":"The Crypto Mullet: Building web 3 in a web 2 world","description":"","start":1695470400000,"end":1695472200000,"stageId":"main_stage__beneath_the_baobabs","speakers":[{"id":"gwera_kiwana","name":"Gwera Kiwana","bio":"Founder in Residence: Crypto","eventId":"eth_safari_2023","twitter":"Women Who Build Africa / Safari DAO / Africa Defi Alliance"}],"playbackId":"","eventId":"eth_safari_2023","coverImage":"/sessions/eth_safari_2023/the_crypto_mullet_building_web_3_in_a_web_2_world.jpg"}