{
    "id": "improving_lighthouse",
    "name": "Improving Lighthouse",
    "description": "Fellow project presentation by Joel",
    "start": 1700208900000,
    "end": 1700209500000,
    "stageId": "3b36",
    "speakers": [
        {
            "id": "joel_rousseau",
            "name": "Joel Rousseau",
            "bio": "EPF Fellow",
            "eventId": "epf_day",
            "twitter": ""
        }
    ],
    "videoUrl": "https://lp-playback.com/hls/b6eebdbgko95r00s/index.m3u8",
    "eventId": "epf_day",
    "coverImage": "/sessions/epf_day/improving_lighthouse_thumbnail.png",
    "assetId": "b6eeaeec-3f1f-454f-9da7-0dff2fb368c9",
    "sourceId": "e21cdf8d-a4fa-4653-b5eb-aa2af7385f86",
    "videoType": "clip"
}